woke_time_mcp/__init__.py
woke_time_mcp/server.py
woke_time_mcp-0.1.7.dist-info/METADATA
woke_time_mcp-0.1.7.dist-info/WHEEL
woke_time_mcp-0.1.7.dist-info/entry_points.txt
woke_time_mcp-0.1.7.dist-info/top_level.txt
woke_time_mcp-0.1.7.dist-info/RECORD
