Metadata-Version: 2.4
Name: woke-time-mcp
Version: 0.1.7
Summary: Add your description here
Requires-Python: >=3.12
Requires-Dist: fastmcp>=2.13.0.2
